{"v":"5.12.1","fr":25,"ip":0,"op":85,"w":256,"h":256,"nm":"3","ddd":0,"assets":[],"layers":[{"ddd":0,"ind":1,"ty":3,"nm":"Null 1","sr":1,"ks":{"o":{"a":0,"k":0,"ix":11},"r":{"a":0,"k":0,"ix":10},"p":{"a":0,"k":[128,128,0],"ix":2,"l":2},"a":{"a":0,"k":[0,0,0],"ix":1,"l":2},"s":{"a":0,"k":[100,100,100],"ix":6,"l":2}},"ao":0,"ip":0,"op":120,"st":0,"bm":0},{"ddd":0,"ind":2,"ty":4,"nm":"Layer 10","parent":1,"sr":1,"ks":{"o":{"a":1,"k":[{"i":{"x":[0.667],"y":[1]},"o":{"x":[0.333],"y":[0]},"t":48,"s":[0]},{"i":{"x":[0.667],"y":[1]},"o":{"x":[0.333],"y":[0]},"t":50,"s":[100]},{"i":{"x":[0.667],"y":[1]},"o":{"x":[0.333],"y":[0]},"t":52,"s":[0]},{"i":{"x":[0.667],"y":[1]},"o":{"x":[0.333],"y":[0]},"t":54,"s":[100]},{"t":56,"s":[0]}],"ix":11},"r":{"a":0,"k":-36,"ix":10},"p":{"a":0,"k":[11.627,-83.718,0],"ix":2,"l":2},"a":{"a":0,"k":[164.835,69.941,0],"ix":1,"l":2},"s":{"a":0,"k":[138,138,100],"ix":6,"l":2}},"ao":0,"shapes":[{"ty":"gr","it":[{"ty":"gr","it":[{"ind":0,"ty":"sh","ix":1,"ks":{"a":0,"k":{"i":[[0.453,0.216],[-1.062,3.027],[-0.502,-0.099],[1.119,-3.129]],"o":[[-0.467,-0.22],[1.081,-3.02],[0.5,0.094],[-1.1,3.132]],"v":[[-1.994,5.566],[-0.653,-0.216],[1.867,-5.578],[1.087,0.397]],"c":true},"ix":2},"nm":"Path 1","mn":"ADBE Vector Shape - Group","hd":false},{"ty":"fl","c":{"a":0,"k":[0,0,0,1],"ix":4},"o":{"a":0,"k":100,"ix":5},"r":1,"bm":0,"nm":"Fill 1","mn":"ADBE Vector Graphic - Fill","hd":false},{"ty":"tr","p":{"a":0,"k":[0,0],"ix":2},"a":{"a":0,"k":[0,0],"ix":1},"s":{"a":0,"k":[100,100],"ix":3},"r":{"a":0,"k":0,"ix":6},"o":{"a":0,"k":100,"ix":7},"sk":{"a":0,"k":0,"ix":4},"sa":{"a":0,"k":0,"ix":5},"nm":"Transform"}],"nm":"Group 1","np":2,"cix":2,"bm":0,"ix":1,"mn":"ADBE Vector Group","hd":false},{"ty":"tr","p":{"a":0,"k":[155.129,64.843],"ix":2},"a":{"a":0,"k":[0,0],"ix":1},"s":{"a":0,"k":[100,100],"ix":3},"r":{"a":0,"k":0,"ix":6},"o":{"a":0,"k":100,"ix":7},"sk":{"a":0,"k":0,"ix":4},"sa":{"a":0,"k":0,"ix":5},"nm":"Transform"}],"nm":"Group 1","np":1,"cix":2,"bm":0,"ix":1,"mn":"ADBE Vector Group","hd":false},{"ty":"gr","it":[{"ty":"gr","it":[{"ind":0,"ty":"sh","ix":1,"ks":{"a":0,"k":{"i":[[-0.389,-0.349],[0.504,-0.607],[1.104,-0.444],[-0.012,0.489],[-1.844,0.759]],"o":[[0.178,0.173],[-0.497,0.606],[-2.245,0.906],[-0.013,-0.526],[1.859,-0.721]],"v":[[3.541,-1.732],[3.069,-0.451],[0.59,1.277],[-3.613,1.27],[-0.104,-0.433]],"c":true},"ix":2},"nm":"Path 1","mn":"ADBE Vector Shape - Group","hd":false},{"ty":"fl","c":{"a":0,"k":[0,0,0,1],"ix":4},"o":{"a":0,"k":100,"ix":5},"r":1,"bm":0,"nm":"Fill 1","mn":"ADBE Vector Graphic - Fill","hd":false},{"ty":"tr","p":{"a":0,"k":[0,0],"ix":2},"a":{"a":0,"k":[0,0],"ix":1},"s":{"a":0,"k":[100,100],"ix":3},"r":{"a":0,"k":0,"ix":6},"o":{"a":0,"k":100,"ix":7},"sk":{"a":0,"k":0,"ix":4},"sa":{"a":0,"k":0,"ix":5},"nm":"Transform"}],"nm":"Group 1","np":2,"cix":2,"bm":0,"ix":1,"mn":"ADBE Vector Group","hd":false},{"ty":"tr","p":{"a":0,"k":[165.783,81.867],"ix":2},"a":{"a":0,"k":[0,0],"ix":1},"s":{"a":0,"k":[100,100],"ix":3},"r":{"a":0,"k":0,"ix":6},"o":{"a":0,"k":100,"ix":7},"sk":{"a":0,"k":0,"ix":4},"sa":{"a":0,"k":0,"ix":5},"nm":"Transform"}],"nm":"Group 2","np":1,"cix":2,"bm":0,"ix":2,"mn":"ADBE Vector Group","hd":false},{"ty":"gr","it":[{"ty":"gr","it":[{"ind":0,"ty":"sh","ix":1,"ks":{"a":0,"k":{"i":[[-0.395,-0.33],[5.023,-5.125],[0.33,0.376],[-4.956,5.088]],"o":[[0.389,0.321],[-5.008,5.14],[-0.344,-0.388],[4.972,-5.072]],"v":[[9.014,-9.249],[0.947,0.924],[-9.023,9.24],[-0.373,-0.365]],"c":true},"ix":2},"nm":"Path 1","mn":"ADBE Vector Shape - Group","hd":false},{"ty":"fl","c":{"a":0,"k":[0,0,0,1],"ix":4},"o":{"a":0,"k":100,"ix":5},"r":1,"bm":0,"nm":"Fill 1","mn":"ADBE Vector Graphic - Fill","hd":false},{"ty":"tr","p":{"a":0,"k":[0,0],"ix":2},"a":{"a":0,"k":[0,0],"ix":1},"s":{"a":0,"k":[100,100],"ix":3},"r":{"a":0,"k":0,"ix":6},"o":{"a":0,"k":100,"ix":7},"sk":{"a":0,"k":0,"ix":4},"sa":{"a":0,"k":0,"ix":5},"nm":"Transform"}],"nm":"Group 1","np":2,"cix":2,"bm":0,"ix":1,"mn":"ADBE Vector Group","hd":false},{"ty":"tr","p":{"a":0,"k":[167.634,65.475],"ix":2},"a":{"a":0,"k":[0,0],"ix":1},"s":{"a":0,"k":[100,100],"ix":3},"r":{"a":0,"k":0,"ix":6},"o":{"a":0,"k":100,"ix":7},"sk":{"a":0,"k":0,"ix":4},"sa":{"a":0,"k":0,"ix":5},"nm":"Transform"}],"nm":"Group 3","np":1,"cix":2,"bm":0,"ix":3,"mn":"ADBE Vector Group","hd":false}],"ip":48,"op":56,"st":8,"ct":1,"bm":0},{"ddd":0,"ind":3,"ty":4,"nm":"Layer 9","parent":1,"sr":1,"ks":{"o":{"a":1,"k":[{"i":{"x":[0.667],"y":[1]},"o":{"x":[0.333],"y":[0]},"t":38,"s":[0]},{"i":{"x":[0.667],"y":[1]},"o":{"x":[0.333],"y":[0]},"t":40,"s":[100]},{"i":{"x":[0.667],"y":[1]},"o":{"x":[0.333],"y":[0]},"t":42,"s":[0]},{"i":{"x":[0.667],"y":[1]},"o":{"x":[0.333],"y":[0]},"t":44,"s":[100]},{"t":46,"s":[0]}],"ix":11},"r":{"a":0,"k":-36,"ix":10},"p":{"a":0,"k":[11.627,-83.718,0],"ix":2,"l":2},"a":{"a":0,"k":[164.835,69.941,0],"ix":1,"l":2},"s":{"a":0,"k":[138,138,100],"ix":6,"l":2}},"ao":0,"shapes":[{"ty":"gr","it":[{"ty":"gr","it":[{"ind":0,"ty":"sh","ix":1,"ks":{"a":0,"k":{"i":[[0.453,0.216],[-1.062,3.027],[-0.502,-0.099],[1.119,-3.129]],"o":[[-0.467,-0.22],[1.081,-3.02],[0.5,0.094],[-1.1,3.132]],"v":[[-1.994,5.566],[-0.653,-0.216],[1.867,-5.578],[1.087,0.397]],"c":true},"ix":2},"nm":"Path 1","mn":"ADBE Vector Shape - Group","hd":false},{"ty":"fl","c":{"a":0,"k":[0,0,0,1],"ix":4},"o":{"a":0,"k":100,"ix":5},"r":1,"bm":0,"nm":"Fill 1","mn":"ADBE Vector Graphic - Fill","hd":false},{"ty":"tr","p":{"a":0,"k":[0,0],"ix":2},"a":{"a":0,"k":[0,0],"ix":1},"s":{"a":0,"k":[100,100],"ix":3},"r":{"a":0,"k":0,"ix":6},"o":{"a":0,"k":100,"ix":7},"sk":{"a":0,"k":0,"ix":4},"sa":{"a":0,"k":0,"ix":5},"nm":"Transform"}],"nm":"Group 1","np":2,"cix":2,"bm":0,"ix":1,"mn":"ADBE Vector Group","hd":false},{"ty":"tr","p":{"a":0,"k":[155.129,64.843],"ix":2},"a":{"a":0,"k":[0,0],"ix":1},"s":{"a":0,"k":[100,100],"ix":3},"r":{"a":0,"k":0,"ix":6},"o":{"a":0,"k":100,"ix":7},"sk":{"a":0,"k":0,"ix":4},"sa":{"a":0,"k":0,"ix":5},"nm":"Transform"}],"nm":"Group 1","np":1,"cix":2,"bm":0,"ix":1,"mn":"ADBE Vector Group","hd":false},{"ty":"gr","it":[{"ty":"gr","it":[{"ind":0,"ty":"sh","ix":1,"ks":{"a":0,"k":{"i":[[-0.389,-0.349],[0.504,-0.607],[1.104,-0.444],[-0.012,0.489],[-1.844,0.759]],"o":[[0.178,0.173],[-0.497,0.606],[-2.245,0.906],[-0.013,-0.526],[1.859,-0.721]],"v":[[3.541,-1.732],[3.069,-0.451],[0.59,1.277],[-3.613,1.27],[-0.104,-0.433]],"c":true},"ix":2},"nm":"Path 1","mn":"ADBE Vector Shape - Group","hd":false},{"ty":"fl","c":{"a":0,"k":[0,0,0,1],"ix":4},"o":{"a":0,"k":100,"ix":5},"r":1,"bm":0,"nm":"Fill 1","mn":"ADBE Vector Graphic - Fill","hd":false},{"ty":"tr","p":{"a":0,"k":[0,0],"ix":2},"a":{"a":0,"k":[0,0],"ix":1},"s":{"a":0,"k":[100,100],"ix":3},"r":{"a":0,"k":0,"ix":6},"o":{"a":0,"k":100,"ix":7},"sk":{"a":0,"k":0,"ix":4},"sa":{"a":0,"k":0,"ix":5},"nm":"Transform"}],"nm":"Group 1","np":2,"cix":2,"bm":0,"ix":1,"mn":"ADBE Vector Group","hd":false},{"ty":"tr","p":{"a":0,"k":[165.783,81.867],"ix":2},"a":{"a":0,"k":[0,0],"ix":1},"s":{"a":0,"k":[100,100],"ix":3},"r":{"a":0,"k":0,"ix":6},"o":{"a":0,"k":100,"ix":7},"sk":{"a":0,"k":0,"ix":4},"sa":{"a":0,"k":0,"ix":5},"nm":"Transform"}],"nm":"Group 2","np":1,"cix":2,"bm":0,"ix":2,"mn":"ADBE Vector Group","hd":false},{"ty":"gr","it":[{"ty":"gr","it":[{"ind":0,"ty":"sh","ix":1,"ks":{"a":0,"k":{"i":[[-0.395,-0.33],[5.023,-5.125],[0.33,0.376],[-4.956,5.088]],"o":[[0.389,0.321],[-5.008,5.14],[-0.344,-0.388],[4.972,-5.072]],"v":[[9.014,-9.249],[0.947,0.924],[-9.023,9.24],[-0.373,-0.365]],"c":true},"ix":2},"nm":"Path 1","mn":"ADBE Vector Shape - Group","hd":false},{"ty":"fl","c":{"a":0,"k":[0,0,0,1],"ix":4},"o":{"a":0,"k":100,"ix":5},"r":1,"bm":0,"nm":"Fill 1","mn":"ADBE Vector Graphic - Fill","hd":false},{"ty":"tr","p":{"a":0,"k":[0,0],"ix":2},"a":{"a":0,"k":[0,0],"ix":1},"s":{"a":0,"k":[100,100],"ix":3},"r":{"a":0,"k":0,"ix":6},"o":{"a":0,"k":100,"ix":7},"sk":{"a":0,"k":0,"ix":4},"sa":{"a":0,"k":0,"ix":5},"nm":"Transform"}],"nm":"Group 1","np":2,"cix":2,"bm":0,"ix":1,"mn":"ADBE Vector Group","hd":false},{"ty":"tr","p":{"a":0,"k":[167.634,65.475],"ix":2},"a":{"a":0,"k":[0,0],"ix":1},"s":{"a":0,"k":[100,100],"ix":3},"r":{"a":0,"k":0,"ix":6},"o":{"a":0,"k":100,"ix":7},"sk":{"a":0,"k":0,"ix":4},"sa":{"a":0,"k":0,"ix":5},"nm":"Transform"}],"nm":"Group 3","np":1,"cix":2,"bm":0,"ix":3,"mn":"ADBE Vector Group","hd":false}],"ip":38,"op":46,"st":-2,"ct":1,"bm":0},{"ddd":0,"ind":4,"ty":4,"nm":"Layer 8","parent":1,"sr":1,"ks":{"o":{"a":1,"k":[{"i":{"x":[0.667],"y":[1]},"o":{"x":[0.333],"y":[0]},"t":28,"s":[0]},{"i":{"x":[0.667],"y":[1]},"o":{"x":[0.333],"y":[0]},"t":30,"s":[100]},{"i":{"x":[0.667],"y":[1]},"o":{"x":[0.333],"y":[0]},"t":32,"s":[0]},{"i":{"x":[0.667],"y":[1]},"o":{"x":[0.333],"y":[0]},"t":34,"s":[100]},{"t":36,"s":[0]}],"ix":11},"r":{"a":0,"k":-36,"ix":10},"p":{"a":0,"k":[11.627,-83.718,0],"ix":2,"l":2},"a":{"a":0,"k":[164.835,69.941,0],"ix":1,"l":2},"s":{"a":0,"k":[138,138,100],"ix":6,"l":2}},"ao":0,"shapes":[{"ty":"gr","it":[{"ty":"gr","it":[{"ind":0,"ty":"sh","ix":1,"ks":{"a":0,"k":{"i":[[0.453,0.216],[-1.062,3.027],[-0.502,-0.099],[1.119,-3.129]],"o":[[-0.467,-0.22],[1.081,-3.02],[0.5,0.094],[-1.1,3.132]],"v":[[-1.994,5.566],[-0.653,-0.216],[1.867,-5.578],[1.087,0.397]],"c":true},"ix":2},"nm":"Path 1","mn":"ADBE Vector Shape - Group","hd":false},{"ty":"fl","c":{"a":0,"k":[0,0,0,1],"ix":4},"o":{"a":0,"k":100,"ix":5},"r":1,"bm":0,"nm":"Fill 1","mn":"ADBE Vector Graphic - Fill","hd":false},{"ty":"tr","p":{"a":0,"k":[0,0],"ix":2},"a":{"a":0,"k":[0,0],"ix":1},"s":{"a":0,"k":[100,100],"ix":3},"r":{"a":0,"k":0,"ix":6},"o":{"a":0,"k":100,"ix":7},"sk":{"a":0,"k":0,"ix":4},"sa":{"a":0,"k":0,"ix":5},"nm":"Transform"}],"nm":"Group 1","np":2,"cix":2,"bm":0,"ix":1,"mn":"ADBE Vector Group","hd":false},{"ty":"tr","p":{"a":0,"k":[155.129,64.843],"ix":2},"a":{"a":0,"k":[0,0],"ix":1},"s":{"a":0,"k":[100,100],"ix":3},"r":{"a":0,"k":0,"ix":6},"o":{"a":0,"k":100,"ix":7},"sk":{"a":0,"k":0,"ix":4},"sa":{"a":0,"k":0,"ix":5},"nm":"Transform"}],"nm":"Group 1","np":1,"cix":2,"bm":0,"ix":1,"mn":"ADBE Vector Group","hd":false},{"ty":"gr","it":[{"ty":"gr","it":[{"ind":0,"ty":"sh","ix":1,"ks":{"a":0,"k":{"i":[[-0.389,-0.349],[0.504,-0.607],[1.104,-0.444],[-0.012,0.489],[-1.844,0.759]],"o":[[0.178,0.173],[-0.497,0.606],[-2.245,0.906],[-0.013,-0.526],[1.859,-0.721]],"v":[[3.541,-1.732],[3.069,-0.451],[0.59,1.277],[-3.613,1.27],[-0.104,-0.433]],"c":true},"ix":2},"nm":"Path 1","mn":"ADBE Vector Shape - Group","hd":false},{"ty":"fl","c":{"a":0,"k":[0,0,0,1],"ix":4},"o":{"a":0,"k":100,"ix":5},"r":1,"bm":0,"nm":"Fill 1","mn":"ADBE Vector Graphic - Fill","hd":false},{"ty":"tr","p":{"a":0,"k":[0,0],"ix":2},"a":{"a":0,"k":[0,0],"ix":1},"s":{"a":0,"k":[100,100],"ix":3},"r":{"a":0,"k":0,"ix":6},"o":{"a":0,"k":100,"ix":7},"sk":{"a":0,"k":0,"ix":4},"sa":{"a":0,"k":0,"ix":5},"nm":"Transform"}],"nm":"Group 1","np":2,"cix":2,"bm":0,"ix":1,"mn":"ADBE Vector Group","hd":false},{"ty":"tr","p":{"a":0,"k":[165.783,81.867],"ix":2},"a":{"a":0,"k":[0,0],"ix":1},"s":{"a":0,"k":[100,100],"ix":3},"r":{"a":0,"k":0,"ix":6},"o":{"a":0,"k":100,"ix":7},"sk":{"a":0,"k":0,"ix":4},"sa":{"a":0,"k":0,"ix":5},"nm":"Transform"}],"nm":"Group 2","np":1,"cix":2,"bm":0,"ix":2,"mn":"ADBE Vector Group","hd":false},{"ty":"gr","it":[{"ty":"gr","it":[{"ind":0,"ty":"sh","ix":1,"ks":{"a":0,"k":{"i":[[-0.395,-0.33],[5.023,-5.125],[0.33,0.376],[-4.956,5.088]],"o":[[0.389,0.321],[-5.008,5.14],[-0.344,-0.388],[4.972,-5.072]],"v":[[9.014,-9.249],[0.947,0.924],[-9.023,9.24],[-0.373,-0.365]],"c":true},"ix":2},"nm":"Path 1","mn":"ADBE Vector Shape - Group","hd":false},{"ty":"fl","c":{"a":0,"k":[0,0,0,1],"ix":4},"o":{"a":0,"k":100,"ix":5},"r":1,"bm":0,"nm":"Fill 1","mn":"ADBE Vector Graphic - Fill","hd":false},{"ty":"tr","p":{"a":0,"k":[0,0],"ix":2},"a":{"a":0,"k":[0,0],"ix":1},"s":{"a":0,"k":[100,100],"ix":3},"r":{"a":0,"k":0,"ix":6},"o":{"a":0,"k":100,"ix":7},"sk":{"a":0,"k":0,"ix":4},"sa":{"a":0,"k":0,"ix":5},"nm":"Transform"}],"nm":"Group 1","np":2,"cix":2,"bm":0,"ix":1,"mn":"ADBE Vector Group","hd":false},{"ty":"tr","p":{"a":0,"k":[167.634,65.475],"ix":2},"a":{"a":0,"k":[0,0],"ix":1},"s":{"a":0,"k":[100,100],"ix":3},"r":{"a":0,"k":0,"ix":6},"o":{"a":0,"k":100,"ix":7},"sk":{"a":0,"k":0,"ix":4},"sa":{"a":0,"k":0,"ix":5},"nm":"Transform"}],"nm":"Group 3","np":1,"cix":2,"bm":0,"ix":3,"mn":"ADBE Vector Group","hd":false}],"ip":28,"op":36,"st":-12,"ct":1,"bm":0},{"ddd":0,"ind":5,"ty":4,"nm":"Layer 2","parent":1,"sr":1,"ks":{"o":{"a":0,"k":100,"ix":11},"r":{"a":1,"k":[{"i":{"x":[0.25],"y":[1]},"o":{"x":[0.33],"y":[0]},"t":2.678,"s":[0]},{"i":{"x":[0.67],"y":[1]},"o":{"x":[0.33],"y":[0]},"t":15.654,"s":[-41]},{"i":{"x":[0.67],"y":[1]},"o":{"x":[0.33],"y":[0]},"t":23.212,"s":[-11]},{"i":{"x":[0.67],"y":[1]},"o":{"x":[0.33],"y":[0]},"t":30.77,"s":[-41]},{"i":{"x":[0.67],"y":[1]},"o":{"x":[0.33],"y":[0]},"t":38.327,"s":[-11]},{"i":{"x":[0.67],"y":[1]},"o":{"x":[0.33],"y":[0]},"t":45.885,"s":[-41]},{"i":{"x":[0.67],"y":[1]},"o":{"x":[0.33],"y":[0]},"t":53.442,"s":[-11]},{"i":{"x":[0.25],"y":[1]},"o":{"x":[0.33],"y":[0]},"t":61,"s":[-41]},{"t":77.677734375,"s":[0]}],"ix":10},"p":{"a":1,"k":[{"i":{"x":0.25,"y":1},"o":{"x":0.33,"y":0},"t":0,"s":[-59.285,41.571,0],"to":[0,0,0],"ti":[0,0,0]},{"i":{"x":0.67,"y":1},"o":{"x":0.33,"y":0},"t":13.387,"s":[-47.285,43.071,0],"to":[0,0,0],"ti":[0,0,0]},{"i":{"x":0.67,"y":1},"o":{"x":0.33,"y":0},"t":20.944,"s":[-40.285,38.071,0],"to":[0,0,0],"ti":[0,0,0]},{"i":{"x":0.67,"y":1},"o":{"x":0.33,"y":0},"t":28.502,"s":[-47.285,43.071,0],"to":[0,0,0],"ti":[0,0,0]},{"i":{"x":0.67,"y":1},"o":{"x":0.33,"y":0},"t":36.06,"s":[-40.285,38.071,0],"to":[0,0,0],"ti":[0,0,0]},{"i":{"x":0.67,"y":1},"o":{"x":0.33,"y":0},"t":43.617,"s":[-47.285,43.071,0],"to":[0,0,0],"ti":[0,0,0]},{"i":{"x":0.67,"y":1},"o":{"x":0.33,"y":0},"t":51.175,"s":[-40.285,38.071,0],"to":[0,0,0],"ti":[0,0,0]},{"i":{"x":0.25,"y":1},"o":{"x":0.33,"y":0},"t":58.732,"s":[-47.285,43.071,0],"to":[0,0,0],"ti":[0,0,0]},{"t":75,"s":[-59.285,41.571,0]}],"ix":2,"l":2},"a":{"a":0,"k":[68.715,169.571,0],"ix":1,"l":2},"s":{"a":0,"k":[100,100,100],"ix":6,"l":2}},"ao":0,"shapes":[{"ty":"gr","it":[{"ind":0,"ty":"sh","ix":1,"ks":{"a":0,"k":{"i":[[0,-1.06],[2.848,0],[0,1.06],[-2.848,0]],"o":[[0,1.06],[-2.848,0],[0,-1.06],[2.848,0]],"v":[[5.157,0],[0,1.919],[-5.157,0],[0,-1.919]],"c":true},"ix":2},"nm":"Path 1","mn":"ADBE Vector Shape - Group","hd":false},{"ty":"fl","c":{"a":0,"k":[0,0,0,1],"ix":4},"o":{"a":0,"k":100,"ix":5},"r":1,"bm":0,"nm":"Fill 1","mn":"ADBE Vector Graphic - Fill","hd":false},{"ty":"tr","p":{"a":0,"k":[105.876,119.998],"ix":2},"a":{"a":0,"k":[0,0],"ix":1},"s":{"a":0,"k":[100,100],"ix":3},"r":{"a":0,"k":0,"ix":6},"o":{"a":0,"k":100,"ix":7},"sk":{"a":0,"k":0,"ix":4},"sa":{"a":0,"k":0,"ix":5},"nm":"Transform"}],"nm":"Group 1","np":2,"cix":2,"bm":0,"ix":1,"mn":"ADBE Vector Group","hd":false},{"ty":"gr","it":[{"ty":"gr","it":[{"ind":0,"ty":"sh","ix":1,"ks":{"a":0,"k":{"i":[[0,-1.267],[1.648,-0.422],[0,-1.051],[0,0],[1.271,1.295],[0,0],[0.816,0.177],[0,0.808],[-3.805,0]],"o":[[0,0.745],[-0.972,0.249],[0,0],[-1.974,1.225],[0,0],[0,-0.875],[-1.858,-0.404],[0,-1.267],[3.805,0]],"v":[[6.891,-3.165],[4.187,-1.339],[2.506,0.841],[2.506,4.535],[-2.39,4.535],[-2.39,0.544],[-3.803,-1.256],[-6.891,-3.165],[0,-5.48]],"c":true},"ix":2},"nm":"Path 1","mn":"ADBE Vector Shape - Group","hd":false},{"ty":"fl","c":{"a":0,"k":[0,0,0,1],"ix":4},"o":{"a":0,"k":100,"ix":5},"r":1,"bm":0,"nm":"Fill 1","mn":"ADBE Vector Graphic - Fill","hd":false},{"ty":"tr","p":{"a":0,"k":[97.941,114.801],"ix":2},"a":{"a":0,"k":[0.062,5.5],"ix":1},"s":{"a":1,"k":[{"i":{"x":[0.667,0.667],"y":[1,1]},"o":{"x":[0.333,0.333],"y":[0,0]},"t":9,"s":[100,100]},{"i":{"x":[0.833,0.833],"y":[1,1]},"o":{"x":[0.333,0.333],"y":[0,0]},"t":14,"s":[100,75]},{"i":{"x":[0.667,0.667],"y":[1,1]},"o":{"x":[0.333,0.333],"y":[0,0]},"t":19,"s":[100,100]},{"i":{"x":[0.833,0.833],"y":[1,1]},"o":{"x":[0.333,0.333],"y":[0,0]},"t":24,"s":[100,75]},{"i":{"x":[0.667,0.667],"y":[1,1]},"o":{"x":[0.333,0.333],"y":[0,0]},"t":29,"s":[100,100]},{"i":{"x":[0.833,0.833],"y":[1,1]},"o":{"x":[0.333,0.333],"y":[0,0]},"t":34,"s":[100,75]},{"i":{"x":[0.667,0.667],"y":[1,1]},"o":{"x":[0.333,0.333],"y":[0,0]},"t":39,"s":[100,100]},{"i":{"x":[0.833,0.833],"y":[1,1]},"o":{"x":[0.333,0.333],"y":[0,0]},"t":44,"s":[100,75]},{"i":{"x":[0.667,0.667],"y":[1,1]},"o":{"x":[0.333,0.333],"y":[0,0]},"t":49,"s":[100,100]},{"i":{"x":[0.833,0.833],"y":[1,1]},"o":{"x":[0.333,0.333],"y":[0,0]},"t":54,"s":[100,75]},{"i":{"x":[0.667,0.667],"y":[1,1]},"o":{"x":[0.333,0.333],"y":[0,0]},"t":59,"s":[100,100]},{"i":{"x":[0.667,0.667],"y":[1,1]},"o":{"x":[0.333,0.333],"y":[0,0]},"t":64,"s":[100,75]},{"t":69,"s":[100,100]}],"ix":3},"r":{"a":0,"k":0,"ix":6},"o":{"a":0,"k":100,"ix":7},"sk":{"a":0,"k":0,"ix":4},"sa":{"a":0,"k":0,"ix":5},"nm":"Transform"}],"nm":"Group 1","np":2,"cix":2,"bm":0,"ix":1,"mn":"ADBE Vector Group","hd":false},{"ty":"gr","it":[{"ty":"gr","it":[{"ty":"gr","it":[{"ind":0,"ty":"sh","ix":1,"ks":{"a":0,"k":{"i":[[0.037,0.072],[-1.1,0.821],[-1.427,2.146],[-0.503,3.624],[1.127,4.503],[2.752,4.711],[4.623,3.986],[0,0],[0,0],[0.623,0.469],[0.664,0.424],[0,0],[0,0],[3.164,0.846],[0.808,0.176],[0.808,0.014],[1.585,-0.394],[2.254,-2.469],[0.664,-2.263],[0.357,-2.644],[0,0],[-0.657,1.581],[-1.388,1.134],[-1.676,0.192],[-1.537,-0.357],[-0.731,-0.271],[-0.367,-0.165],[0,0],[-1.261,-0.694],[-0.629,-0.329],[-0.602,-0.36],[-1.139,-0.755],[-2.893,-3.852],[-1.504,-3.761],[-0.244,-4.419],[0.159,0.017],[0.515,4.351],[3.138,7.22],[2.813,3.672],[4.287,3.006],[1.184,0.642],[0.588,0.342],[0.614,0.312],[1.292,0.564],[0,0],[0.317,0.113],[0.662,0.149],[1.954,-1.643],[0.377,-2.924],[0,0],[-0.11,1.317],[-0.402,1.372],[-1.923,2.121],[-3.668,0.885],[-1.854,-0.074],[-0.892,-0.15],[-0.862,-0.192],[-2.917,-1.705],[0,0],[0,0],[-0.69,-0.45],[-0.645,-0.495],[0,0],[0,0],[-2.755,-4.97],[-0.984,-4.726],[0.666,-3.807],[1.666,-2.158],[1.199,-0.74]],"o":[[-0.05,-0.091],[1.068,-0.859],[1.444,-2.125],[0.492,-3.624],[-1.06,-4.513],[-2.723,-4.724],[0,0],[0,0],[-0.616,-0.464],[-0.657,-0.419],[0,0],[0,0],[-2.761,-1.589],[-0.801,-0.175],[-0.801,-0.129],[-1.607,-0.058],[-3.176,0.773],[-1.652,1.807],[-0.675,2.248],[0,0],[0.225,-1.644],[0.639,-1.578],[1.394,-1.133],[1.684,-0.189],[0.77,0.181],[0.367,0.135],[0,0],[1.34,0.599],[0.636,0.333],[0.61,0.364],[1.225,0.686],[4.439,3.206],[2.855,3.888],[3.017,7.545],[0.226,4.444],[-0.175,-0.009],[-0.53,-4.326],[-1.563,-3.6],[-2.853,-3.636],[-1.103,-0.706],[-0.581,-0.338],[-0.607,-0.308],[-1.214,-0.652],[0,0],[-0.294,-0.129],[-0.635,-0.229],[-2.63,-0.599],[-1.99,1.609],[0,0],[0.153,-1.221],[0.114,-1.314],[0.811,-2.75],[2.613,-2.865],[1.831,-0.451],[0.925,0.021],[0.87,0.194],[3.398,0.922],[0,0],[0,0],[0.698,0.455],[0.653,0.501],[0,0],[0,0],[4.814,4.241],[2.782,4.957],[1.052,4.716],[-0.675,3.814],[-1.649,2.182],[-1.233,0.701]],"v":[[19.953,33.182],[21.608,31.843],[25.636,27.487],[28.784,18.756],[27.961,6.391],[22.301,-7.628],[11.212,-20.909],[10.348,-21.666],[9.426,-22.359],[7.566,-23.76],[5.585,-25.025],[4.586,-25.662],[3.535,-26.216],[-5.46,-29.763],[-7.874,-30.289],[-10.269,-30.54],[-15.088,-30.039],[-23.483,-25.028],[-27.096,-18.759],[-28.072,-11.29],[-30.691,-11.624],[-29.445,-16.494],[-26.402,-20.714],[-21.6,-22.675],[-16.744,-22.338],[-14.494,-21.663],[-13.402,-21.217],[-12.443,-20.786],[-8.501,-18.933],[-6.604,-17.94],[-4.785,-16.854],[-1.315,-14.566],[9.687,-3.767],[16.178,7.844],[20.273,26.325],[19.953,33.182],[19.327,26.406],[14.565,8.522],[8.037,-2.512],[-2.668,-12.664],[-6.018,-14.808],[-7.772,-15.827],[-9.604,-16.757],[-13.407,-18.495],[-14.427,-18.941],[-15.352,-19.308],[-17.306,-19.876],[-24.77,-18.699],[-28.072,-11.29],[-30.691,-11.624],[-30.345,-15.411],[-29.654,-19.497],[-25.455,-26.827],[-15.732,-32.616],[-10.167,-33.177],[-7.422,-32.878],[-4.824,-32.3],[4.762,-28.451],[5.873,-27.851],[6.926,-27.17],[9.008,-25.811],[10.955,-24.318],[11.918,-23.576],[12.818,-22.772],[24.219,-8.732],[29.804,5.983],[30.259,18.988],[26.485,28.086],[21.914,32.285]],"c":true},"ix":2},"nm":"Path 1","mn":"ADBE Vector Shape - Group","hd":false},{"ty":"fl","c":{"a":0,"k":[0,0,0,1],"ix":4},"o":{"a":0,"k":100,"ix":5},"r":1,"bm":0,"nm":"Fill 1","mn":"ADBE Vector Graphic - Fill","hd":false},{"ty":"tr","p":{"a":0,"k":[0,0],"ix":2},"a":{"a":0,"k":[0,0],"ix":1},"s":{"a":0,"k":[100,100],"ix":3},"r":{"a":0,"k":0,"ix":6},"o":{"a":0,"k":100,"ix":7},"sk":{"a":0,"k":0,"ix":4},"sa":{"a":0,"k":0,"ix":5},"nm":"Transform"}],"nm":"Group 1","np":2,"cix":2,"bm":0,"ix":1,"mn":"ADBE Vector Group","hd":false},{"ty":"tr","p":{"a":0,"k":[101.065,98.058],"ix":2},"a":{"a":0,"k":[0,0],"ix":1},"s":{"a":0,"k":[100,100],"ix":3},"r":{"a":0,"k":0,"ix":6},"o":{"a":0,"k":100,"ix":7},"sk":{"a":0,"k":0,"ix":4},"sa":{"a":0,"k":0,"ix":5},"nm":"Transform"}],"nm":"Group 1","np":1,"cix":2,"bm":0,"ix":1,"mn":"ADBE Vector Group","hd":false},{"ty":"gr","it":[{"ind":0,"ty":"sh","ix":1,"ks":{"a":0,"k":{"i":[[8.996,-4.817],[36.705,14.843],[1.953,-15.3],[-1.713,3.593],[-7.908,-1.335],[-3.27,-18.993]],"o":[[0,0],[0,0],[0.489,-3.835],[3.623,-7.599],[18.37,3.1],[1.671,9.705]],"v":[[19.708,32.534],[-13.969,-20.639],[-29.626,-12.105],[-27.732,-22.106],[-8.097,-32.276],[29.097,7.696]],"c":true},"ix":2},"nm":"Path 1","mn":"ADBE Vector Shape - Group","hd":false},{"ty":"fl","c":{"a":0,"k":[1,1,1,1],"ix":4},"o":{"a":0,"k":100,"ix":5},"r":1,"bm":0,"nm":"Fill 1","mn":"ADBE Vector Graphic - Fill","hd":false},{"ty":"tr","p":{"a":0,"k":[101.31,98.706],"ix":2},"a":{"a":0,"k":[0,0],"ix":1},"s":{"a":0,"k":[100,100],"ix":3},"r":{"a":0,"k":0,"ix":6},"o":{"a":0,"k":100,"ix":7},"sk":{"a":0,"k":0,"ix":4},"sa":{"a":0,"k":0,"ix":5},"nm":"Transform"}],"nm":"Group 2","np":2,"cix":2,"bm":0,"ix":2,"mn":"ADBE Vector Group","hd":false},{"ty":"tr","p":{"a":0,"k":[101.31,98.706],"ix":2},"a":{"a":0,"k":[101.31,98.706],"ix":1},"s":{"a":0,"k":[100,100],"ix":3},"r":{"a":0,"k":0,"ix":6},"o":{"a":0,"k":100,"ix":7},"sk":{"a":0,"k":0,"ix":4},"sa":{"a":0,"k":0,"ix":5},"nm":"Transform"}],"nm":"Group 2","np":2,"cix":2,"bm":0,"ix":2,"mn":"ADBE Vector Group","hd":false},{"ty":"gr","it":[{"ind":0,"ty":"sh","ix":1,"ks":{"a":0,"k":{"i":[[0,0],[0.441,-1.998],[0,0],[-3.504,0.512]],"o":[[-0.418,2.193],[0,0],[-1.555,-3.485],[0,0]],"v":[[5.013,-2.344],[3.289,4.703],[-4.16,1.608],[-1.77,-4.703]],"c":true},"ix":2},"nm":"Path 1","mn":"ADBE Vector Shape - Group","hd":false},{"ty":"fl","c":{"a":0,"k":[0,0,0,1],"ix":4},"o":{"a":0,"k":100,"ix":5},"r":1,"bm":0,"nm":"Fill 1","mn":"ADBE Vector Graphic - Fill","hd":false},{"ty":"tr","p":{"a":0,"k":[89.232,139.605],"ix":2},"a":{"a":0,"k":[0,0],"ix":1},"s":{"a":0,"k":[100,100],"ix":3},"r":{"a":0,"k":0,"ix":6},"o":{"a":0,"k":100,"ix":7},"sk":{"a":0,"k":0,"ix":4},"sa":{"a":0,"k":0,"ix":5},"nm":"Transform"}],"nm":"Group 3","np":2,"cix":2,"bm":0,"ix":3,"mn":"ADBE Vector Group","hd":false},{"ty":"gr","it":[{"ty":"gr","it":[{"ty":"gr","it":[{"ind":0,"ty":"sh","ix":1,"ks":{"a":0,"k":{"i":[[-0.018,-0.168],[2.476,-0.601],[1.676,-0.599],[0.868,-0.456],[0.658,-0.705],[-0.321,-0.771],[-1.033,-0.66],[-2.843,-0.778],[-6.899,-0.077],[-3.209,0.399],[-2.652,1.058],[-0.744,0.818],[-0.04,0.389],[0.332,0.431],[0.977,0.623],[1.034,0.422],[2.478,0.584],[-0.024,0.205],[-2.58,-0.265],[-4.458,-1.582],[-1.168,-0.632],[-0.973,-1.365],[-0.008,-0.991],[0.573,-0.672],[1.473,-0.651],[3.345,-0.465],[3.56,0.031],[5.982,1.729],[2.412,1.664],[0.559,1.587],[-0.278,0.75],[-0.463,0.487],[-0.994,0.443],[-0.902,0.257],[-1.292,0.152]],"o":[[0.023,0.198],[-1.235,0.303],[-0.832,0.309],[-0.864,0.446],[-0.656,0.719],[0.303,0.801],[2.093,1.346],[5.732,1.522],[3.45,0.03],[3.198,-0.404],[1.308,-0.525],[0.366,-0.409],[-0.032,-0.39],[-0.56,-0.876],[-1.013,-0.604],[-4.132,-1.72],[-2.492,-0.574],[0.018,-0.161],[2.573,0.28],[1.115,0.39],[1.145,0.68],[0.51,0.644],[-0.049,1.014],[-1.178,1.345],[-2.974,1.259],[-3.348,0.453],[-7.115,-0.082],[-2.98,-0.895],[-1.174,-0.844],[-0.28,-0.787],[0.26,-0.784],[0.976,-0.924],[0.998,-0.444],[1.809,-0.491],[2.586,-0.296]],"v":[[-12.088,-8.855],[-15.943,-7.77],[-20.361,-6.477],[-22.947,-5.37],[-25.368,-3.68],[-26.018,-1.419],[-23.808,0.866],[-16.186,3.943],[3.041,6.325],[13.069,5.79],[21.999,3.708],[25.278,1.684],[25.879,0.478],[25.484,-0.775],[22.95,-3.023],[19.87,-4.577],[9.621,-7.677],[5.753,-8.739],[9.79,-8.702],[20.564,-6.332],[23.994,-4.799],[27.332,-1.993],[28.159,0.608],[27.058,3.214],[22.951,5.976],[13.408,8.383],[3.017,8.994],[-16.852,6.311],[-25.054,2.696],[-27.967,-0.75],[-27.93,-3.208],[-26.703,-5.014],[-23.674,-6.904],[-20.809,-7.9],[-16.129,-8.793]],"c":true},"ix":2},"nm":"Path 1","mn":"ADBE Vector Shape - Group","hd":false},{"ty":"fl","c":{"a":0,"k":[0,0,0,1],"ix":4},"o":{"a":0,"k":100,"ix":5},"r":1,"bm":0,"nm":"Fill 1","mn":"ADBE Vector Graphic - Fill","hd":false},{"ty":"tr","p":{"a":0,"k":[0,0],"ix":2},"a":{"a":0,"k":[0,0],"ix":1},"s":{"a":0,"k":[100,100],"ix":3},"r":{"a":0,"k":0,"ix":6},"o":{"a":0,"k":100,"ix":7},"sk":{"a":0,"k":0,"ix":4},"sa":{"a":0,"k":0,"ix":5},"nm":"Transform"}],"nm":"Group 1","np":2,"cix":2,"bm":0,"ix":1,"mn":"ADBE Vector Group","hd":false},{"ty":"tr","p":{"a":0,"k":[101.87,118.196],"ix":2},"a":{"a":0,"k":[0,0],"ix":1},"s":{"a":0,"k":[100,100],"ix":3},"r":{"a":0,"k":0,"ix":6},"o":{"a":0,"k":100,"ix":7},"sk":{"a":0,"k":0,"ix":4},"sa":{"a":0,"k":0,"ix":5},"nm":"Transform"}],"nm":"Group 1","np":1,"cix":2,"bm":0,"ix":1,"mn":"ADBE Vector Group","hd":false},{"ty":"gr","it":[{"ind":0,"ty":"sh","ix":1,"ks":{"a":0,"k":{"i":[[0,0],[0.178,-4.044],[14.962,0.726],[-0.203,4.621],[-8.814,0.962]],"o":[[12.31,1.379],[-0.203,4.621],[-14.962,-0.726],[0.143,-3.247],[0,0]],"v":[[5.82,-8.144],[27.09,1.103],[-0.368,8.156],[-27.09,-1.526],[-12.021,-8.26]],"c":false},"ix":2},"nm":"Path 1","mn":"ADBE Vector Shape - Group","hd":false},{"ty":"fl","c":{"a":0,"k":[1,1,1,1],"ix":4},"o":{"a":0,"k":100,"ix":5},"r":1,"bm":0,"nm":"Fill 1","mn":"ADBE Vector Graphic - Fill","hd":false},{"ty":"tr","p":{"a":0,"k":[101.803,117.602],"ix":2},"a":{"a":0,"k":[0,0],"ix":1},"s":{"a":0,"k":[100,100],"ix":3},"r":{"a":0,"k":0,"ix":6},"o":{"a":0,"k":100,"ix":7},"sk":{"a":0,"k":0,"ix":4},"sa":{"a":0,"k":0,"ix":5},"nm":"Transform"}],"nm":"Group 2","np":2,"cix":2,"bm":0,"ix":2,"mn":"ADBE Vector Group","hd":false},{"ty":"tr","p":{"a":0,"k":[101.803,117.602],"ix":2},"a":{"a":0,"k":[101.803,117.602],"ix":1},"s":{"a":0,"k":[100,100],"ix":3},"r":{"a":0,"k":0,"ix":6},"o":{"a":0,"k":100,"ix":7},"sk":{"a":0,"k":0,"ix":4},"sa":{"a":0,"k":0,"ix":5},"nm":"Transform"}],"nm":"Group 4","np":2,"cix":2,"bm":0,"ix":4,"mn":"ADBE Vector Group","hd":false},{"ty":"gr","it":[{"ty":"gr","it":[{"ty":"gr","it":[{"ind":0,"ty":"sh","ix":1,"ks":{"a":0,"k":{"i":[[0.01,-0.092],[1.619,0.089],[3.066,0.254],[10.948,1.071],[2.987,0.295],[1.552,0.156],[0.766,0.077],[0.017,-0.095],[0,0],[3.132,-6.531],[2.649,-7.381],[0.848,-3.903],[-1.296,-3.594],[-1.12,-1.583],[-1.561,-0.773],[-1.751,0.303],[-1.569,0.996],[-0.661,0.524],[-0.564,0.717],[-0.953,1.597],[-1.391,3.31],[-1.601,6.22],[-0.366,1.508],[-0.311,1.461],[-0.09,0.427],[0,0],[0,0],[0,0],[-0.072,-0.005],[-0.596,-0.077],[-0.193,-0.019],[0,0],[-1.345,0.021],[-2.368,0.502],[-0.567,0.152],[-0.54,0.177],[-0.949,0.483],[-2.004,2.23],[-0.424,0.517],[-0.33,0.48],[-0.264,0.417],[-0.185,0.356],[-0.087,-0.03],[0.551,-1.544],[0.224,-0.453],[0.281,-0.53],[0.419,-0.554],[0.463,-0.634],[4.07,-1.911],[1.11,-0.448],[0.59,-0.179],[0.623,-0.115],[2.803,-0.106],[1.475,0.086],[0.335,0.024],[0,0],[0.031,-0.066],[0,0],[0.3,-1.538],[0.359,-1.586],[2.772,-6.821],[1.966,-3.356],[1.252,-1.589],[0.847,-0.8],[0.904,-0.562],[2.208,-0.423],[2.078,1.118],[1.275,1.764],[0.737,2.126],[-0.096,2.149],[-0.413,2.054],[-1.354,3.757],[-3.199,6.56],[-3.206,5.646],[-0.264,0.46],[-0.683,-0.016],[-0.799,-0.093],[-1.491,-0.175],[-2.731,-0.325],[-6.098,-0.825],[-1.6,-0.262]],"o":[[-0.01,0.092],[-1.619,-0.089],[-6.133,-0.507],[-2.737,-0.271],[-1.494,-0.15],[-0.752,-0.076],[-0.07,0.001],[0,0],[-3.098,5.648],[-3.114,6.537],[-1.312,3.69],[-0.759,3.889],[0.635,1.84],[1.132,1.575],[1.542,0.83],[1.753,-0.33],[0.782,-0.474],[0.581,-0.544],[1.162,-1.455],[1.904,-3.2],[2.768,-6.633],[0.379,-1.562],[0.323,-1.519],[0.091,-0.432],[0,0],[0,0],[0,0],[0.061,-0.013],[0.603,0.077],[0.352,0.048],[0,0],[1.397,0.109],[2.69,-0.043],[0.6,-0.094],[0.566,-0.155],[1.063,-0.397],[3.919,-1.688],[0.478,-0.583],[0.437,-0.509],[0.313,-0.493],[0.257,-0.422],[0.697,-1.444],[0.087,0.03],[-0.149,0.381],[-0.237,0.448],[-0.303,0.518],[-0.411,0.562],[-1.965,2.435],[-0.989,0.54],[-0.563,0.202],[-0.591,0.175],[-2.467,0.59],[-1.403,0.052],[-0.331,-0.024],[0,0],[-0.093,0.017],[0,0],[-0.289,1.48],[-0.346,1.53],[-1.528,6.321],[-1.395,3.406],[-0.986,1.677],[-0.637,0.807],[-0.866,0.703],[-1.764,1.126],[-2.198,0.406],[-2.12,-1.069],[-1.272,-1.798],[-0.775,-2.124],[0.114,-2.176],[0.897,-4.084],[2.733,-7.507],[3.218,-6.553],[0.266,-0.464],[0.205,-0.941],[0.813,0.095],[1.549,0.182],[2.981,0.355],[10.921,1.311],[3.049,0.412],[1.6,0.262]],"v":[[38.305,-32.074],[35.821,-32.074],[28.752,-32.592],[2.807,-34.991],[-5.784,-35.84],[-10.353,-36.298],[-12.631,-36.527],[-12.807,-36.47],[-13.199,-35.755],[-22.593,-17.448],[-31.465,3.418],[-34.822,14.815],[-34.904,26.379],[-32.214,31.574],[-28.217,35.333],[-23.151,36.042],[-18.114,33.964],[-15.883,32.371],[-14.087,30.363],[-10.935,25.742],[-6.037,15.918],[0.305,-3.526],[1.424,-8.131],[2.376,-12.602],[2.647,-13.89],[2.846,-14.85],[2.945,-15.325],[2.994,-15.562],[3.214,-15.544],[5.013,-15.313],[5.653,-15.244],[6.176,-15.197],[10.3,-15.058],[17.927,-15.831],[19.67,-16.228],[21.345,-16.68],[24.436,-17.836],[33.251,-24.127],[34.604,-25.777],[35.641,-27.34],[36.508,-28.705],[37.107,-29.905],[38.305,-32.074],[37.598,-29.685],[37.103,-28.404],[36.325,-26.936],[35.357,-25.251],[34.045,-23.458],[25.051,-16.476],[21.837,-15.16],[20.095,-14.636],[18.281,-14.17],[10.342,-13.171],[6.029,-13.227],[5.03,-13.299],[4.651,-13.334],[4.569,-13.106],[4.396,-12.198],[3.513,-7.67],[2.454,-2.996],[-3.764,16.86],[-8.745,27.048],[-12.061,31.969],[-14.162,34.322],[-16.722,36.178],[-22.684,38.639],[-29.438,37.692],[-34.386,33.121],[-37.43,27.243],[-38.3,20.588],[-37.42,14.264],[-33.926,2.533],[-24.807,-18.52],[-15.13,-36.837],[-14.335,-38.225],[-12.54,-38.707],[-10.122,-38.425],[-5.561,-37.888],[3.012,-36.868],[28.864,-33.625],[35.879,-32.609]],"c":true},"ix":2},"nm":"Path 1","mn":"ADBE Vector Shape - Group","hd":false},{"ty":"fl","c":{"a":0,"k":[0,0,0,1],"ix":4},"o":{"a":0,"k":100,"ix":5},"r":1,"bm":0,"nm":"Fill 1","mn":"ADBE Vector Graphic - Fill","hd":false},{"ty":"tr","p":{"a":0,"k":[0,0],"ix":2},"a":{"a":0,"k":[0,0],"ix":1},"s":{"a":0,"k":[100,100],"ix":3},"r":{"a":0,"k":0,"ix":6},"o":{"a":0,"k":100,"ix":7},"sk":{"a":0,"k":0,"ix":4},"sa":{"a":0,"k":0,"ix":5},"nm":"Transform"}],"nm":"Group 1","np":2,"cix":2,"bm":0,"ix":1,"mn":"ADBE Vector Group","hd":false},{"ty":"tr","p":{"a":0,"k":[89.996,152.452],"ix":2},"a":{"a":0,"k":[0,0],"ix":1},"s":{"a":0,"k":[100,100],"ix":3},"r":{"a":0,"k":0,"ix":6},"o":{"a":0,"k":100,"ix":7},"sk":{"a":0,"k":0,"ix":4},"sa":{"a":0,"k":0,"ix":5},"nm":"Transform"}],"nm":"Group 1","np":1,"cix":2,"bm":0,"ix":1,"mn":"ADBE Vector Group","hd":false},{"ty":"gr","it":[{"ind":0,"ty":"sh","ix":1,"ks":{"a":0,"k":{"i":[[0,0],[5.592,0.536],[0,0],[0.441,-1.998],[0,0],[5.035,4.752],[0.557,3.728],[0,0]],"o":[[-6.59,19.032],[-0.882,-0.098],[-0.418,2.193],[-7.124,32.654],[-4.757,3.85],[-2.622,-2.461],[-2.483,-16.814],[0,0]],"v":[[37.65,-31.979],[4.539,-14.19],[3.147,-14.361],[1.87,-8.049],[-15.741,33.499],[-31.798,34.961],[-37.483,24.288],[-14.024,-37.608]],"c":true},"ix":2},"nm":"Path 1","mn":"ADBE Vector Shape - Group","hd":false},{"ty":"fl","c":{"a":0,"k":[1,1,1,1],"ix":4},"o":{"a":0,"k":100,"ix":5},"r":1,"bm":0,"nm":"Fill 1","mn":"ADBE Vector Graphic - Fill","hd":false},{"ty":"tr","p":{"a":0,"k":[90.65,152.357],"ix":2},"a":{"a":0,"k":[0,0],"ix":1},"s":{"a":0,"k":[100,100],"ix":3},"r":{"a":0,"k":0,"ix":6},"o":{"a":0,"k":100,"ix":7},"sk":{"a":0,"k":0,"ix":4},"sa":{"a":0,"k":0,"ix":5},"nm":"Transform"}],"nm":"Group 2","np":2,"cix":2,"bm":0,"ix":2,"mn":"ADBE Vector Group","hd":false},{"ty":"tr","p":{"a":0,"k":[90.65,152.357],"ix":2},"a":{"a":0,"k":[90.65,152.357],"ix":1},"s":{"a":0,"k":[100,100],"ix":3},"r":{"a":0,"k":0,"ix":6},"o":{"a":0,"k":100,"ix":7},"sk":{"a":0,"k":0,"ix":4},"sa":{"a":0,"k":0,"ix":5},"nm":"Transform"}],"nm":"Group 5","np":2,"cix":2,"bm":0,"ix":5,"mn":"ADBE Vector Group","hd":false},{"ty":"gr","it":[{"ind":0,"ty":"sh","ix":1,"ks":{"a":0,"k":{"i":[[0,0],[-19.091,-25.99],[0,0],[-17.324,16.151]],"o":[[0,0],[0,0],[0,0],[0,0]],"v":[[9.065,-18.535],[10.396,16.337],[-3.216,20.05],[-2.509,-20.05]],"c":true},"ix":2},"nm":"Path 1","mn":"ADBE Vector Shape - Group","hd":false},{"ty":"fl","c":{"a":0,"k":[0,0,0,1],"ix":4},"o":{"a":0,"k":100,"ix":5},"r":1,"bm":0,"nm":"Fill 1","mn":"ADBE Vector Graphic - Fill","hd":false},{"ty":"tr","p":{"a":0,"k":[80.359,93.811],"ix":2},"a":{"a":0,"k":[0,0],"ix":1},"s":{"a":0,"k":[100,100],"ix":3},"r":{"a":0,"k":0,"ix":6},"o":{"a":0,"k":100,"ix":7},"sk":{"a":0,"k":0,"ix":4},"sa":{"a":0,"k":0,"ix":5},"nm":"Transform"}],"nm":"Group 6","np":2,"cix":2,"bm":0,"ix":6,"mn":"ADBE Vector Group","hd":false},{"ty":"tr","p":{"a":0,"k":[80.359,93.811],"ix":2},"a":{"a":0,"k":[80.359,93.811],"ix":1},"s":{"a":0,"k":[100,100],"ix":3},"r":{"a":0,"k":0,"ix":6},"o":{"a":0,"k":100,"ix":7},"sk":{"a":0,"k":0,"ix":4},"sa":{"a":0,"k":0,"ix":5},"nm":"Transform"}],"nm":"Group 2","np":6,"cix":2,"bm":0,"ix":2,"mn":"ADBE Vector Group","hd":false}],"ip":0,"op":120,"st":0,"ct":1,"bm":0},{"ddd":0,"ind":6,"ty":4,"nm":"Layer 1","parent":1,"sr":1,"ks":{"o":{"a":0,"k":100,"ix":11},"r":{"a":1,"k":[{"i":{"x":[0.25],"y":[1]},"o":{"x":[0.33],"y":[0]},"t":2.678,"s":[0]},{"i":{"x":[0.67],"y":[1]},"o":{"x":[0.33],"y":[0]},"t":15.654,"s":[30]},{"i":{"x":[0.67],"y":[1]},"o":{"x":[0.33],"y":[0]},"t":23.212,"s":[-6]},{"i":{"x":[0.67],"y":[1]},"o":{"x":[0.33],"y":[0]},"t":30.77,"s":[30]},{"i":{"x":[0.67],"y":[1]},"o":{"x":[0.33],"y":[0]},"t":38.327,"s":[-6]},{"i":{"x":[0.67],"y":[1]},"o":{"x":[0.33],"y":[0]},"t":45.885,"s":[30]},{"i":{"x":[0.67],"y":[1]},"o":{"x":[0.33],"y":[0]},"t":53.442,"s":[-6]},{"i":{"x":[0.25],"y":[1]},"o":{"x":[0.33],"y":[0]},"t":61,"s":[30]},{"t":77.677734375,"s":[0]}],"ix":10},"p":{"a":1,"k":[{"i":{"x":0.25,"y":1},"o":{"x":0.33,"y":0},"t":0,"s":[70.752,54.165,0],"to":[0,0,0],"ti":[0,0,0]},{"i":{"x":0.67,"y":1},"o":{"x":0.33,"y":0},"t":13.387,"s":[58.752,53.665,0],"to":[0,0,0],"ti":[0,0,0]},{"i":{"x":0.67,"y":1},"o":{"x":0.33,"y":0},"t":20.944,"s":[60.252,42.165,0],"to":[0,0,0],"ti":[0,0,0]},{"i":{"x":0.67,"y":1},"o":{"x":0.33,"y":0},"t":28.502,"s":[58.752,53.665,0],"to":[0,0,0],"ti":[0,0,0]},{"i":{"x":0.67,"y":1},"o":{"x":0.33,"y":0},"t":36.06,"s":[60.252,42.165,0],"to":[0,0,0],"ti":[0,0,0]},{"i":{"x":0.67,"y":1},"o":{"x":0.33,"y":0},"t":43.617,"s":[58.752,53.665,0],"to":[0,0,0],"ti":[0,0,0]},{"i":{"x":0.67,"y":1},"o":{"x":0.33,"y":0},"t":51.175,"s":[60.252,42.165,0],"to":[0,0,0],"ti":[0,0,0]},{"i":{"x":0.25,"y":1},"o":{"x":0.33,"y":0},"t":58.732,"s":[58.752,53.665,0],"to":[0,0,0],"ti":[0,0,0]},{"t":75,"s":[70.752,54.165,0]}],"ix":2,"l":2},"a":{"a":0,"k":[189.252,183.165,0],"ix":1,"l":2},"s":{"a":0,"k":[100,100,100],"ix":6,"l":2}},"ao":0,"shapes":[{"ty":"gr","it":[{"ind":0,"ty":"sh","ix":1,"ks":{"a":0,"k":{"i":[[0,-1.06],[2.848,0],[0,1.06],[-2.848,0]],"o":[[0,1.06],[-2.848,0],[0,-1.06],[2.848,0]],"v":[[5.157,0],[0,1.919],[-5.157,0],[0,-1.919]],"c":true},"ix":2},"nm":"Path 1","mn":"ADBE Vector Shape - Group","hd":false},{"ty":"fl","c":{"a":0,"k":[0,0,0,1],"ix":4},"o":{"a":0,"k":100,"ix":5},"r":1,"bm":0,"nm":"Fill 1","mn":"ADBE Vector Graphic - Fill","hd":false},{"ty":"tr","p":{"a":0,"k":[156.793,122.605],"ix":2},"a":{"a":0,"k":[0,0],"ix":1},"s":{"a":0,"k":[100,100],"ix":3},"r":{"a":0,"k":0,"ix":6},"o":{"a":0,"k":100,"ix":7},"sk":{"a":0,"k":0,"ix":4},"sa":{"a":0,"k":0,"ix":5},"nm":"Transform"}],"nm":"Group 1","np":2,"cix":2,"bm":0,"ix":1,"mn":"ADBE Vector Group","hd":false},{"ty":"gr","it":[{"ty":"gr","it":[{"ind":0,"ty":"sh","ix":1,"ks":{"a":0,"k":{"i":[[0.249,-1.242],[-1.569,-0.745],[0.207,-1.031],[0,0],[-1.529,1.014],[0,0],[-0.852,0.01],[-0.159,0.792],[3.815,0.765]],"o":[[-0.146,0.73],[0.926,0.44],[0,0],[1.738,1.598],[0,0],[0.172,-0.858],[1.942,-0.023],[0.249,-1.242],[-3.815,-0.765]],"v":[[-6.908,-4.35],[-4.556,-2.016],[-3.3,0.46],[-4.026,4.081],[0.882,5.065],[1.667,1.152],[3.437,-0.328],[6.908,-1.579],[0.455,-5.234]],"c":true},"ix":2},"nm":"Path 1","mn":"ADBE Vector Shape - Group","hd":false},{"ty":"fl","c":{"a":0,"k":[0,0,0,1],"ix":4},"o":{"a":0,"k":100,"ix":5},"r":1,"bm":0,"nm":"Fill 1","mn":"ADBE Vector Graphic - Fill","hd":false},{"ty":"tr","p":{"a":0,"k":[168.846,120.909],"ix":2},"a":{"a":0,"k":[-2,5.25],"ix":1},"s":{"a":1,"k":[{"i":{"x":[0.667,0.667],"y":[1,1]},"o":{"x":[0.333,0.333],"y":[0,0]},"t":13,"s":[100,100]},{"i":{"x":[0.833,0.833],"y":[1,1]},"o":{"x":[0.333,0.333],"y":[0,0]},"t":18,"s":[100,75]},{"i":{"x":[0.667,0.667],"y":[1,1]},"o":{"x":[0.333,0.333],"y":[0,0]},"t":23,"s":[100,100]},{"i":{"x":[0.833,0.833],"y":[1,1]},"o":{"x":[0.333,0.333],"y":[0,0]},"t":28,"s":[100,75]},{"i":{"x":[0.667,0.667],"y":[1,1]},"o":{"x":[0.333,0.333],"y":[0,0]},"t":33,"s":[100,100]},{"i":{"x":[0.833,0.833],"y":[1,1]},"o":{"x":[0.333,0.333],"y":[0,0]},"t":38,"s":[100,75]},{"i":{"x":[0.667,0.667],"y":[1,1]},"o":{"x":[0.333,0.333],"y":[0,0]},"t":43,"s":[100,100]},{"i":{"x":[0.833,0.833],"y":[1,1]},"o":{"x":[0.333,0.333],"y":[0,0]},"t":48,"s":[100,75]},{"i":{"x":[0.667,0.667],"y":[1,1]},"o":{"x":[0.333,0.333],"y":[0,0]},"t":53,"s":[100,100]},{"i":{"x":[0.833,0.833],"y":[1,1]},"o":{"x":[0.333,0.333],"y":[0,0]},"t":58,"s":[100,75]},{"i":{"x":[0.667,0.667],"y":[1,1]},"o":{"x":[0.333,0.333],"y":[0,0]},"t":63,"s":[100,100]},{"i":{"x":[0.667,0.667],"y":[1,1]},"o":{"x":[0.333,0.333],"y":[0,0]},"t":68,"s":[100,75]},{"t":73,"s":[100,100]}],"ix":3},"r":{"a":0,"k":0,"ix":6},"o":{"a":0,"k":100,"ix":7},"sk":{"a":0,"k":0,"ix":4},"sa":{"a":0,"k":0,"ix":5},"nm":"Transform"}],"nm":"Group 1","np":2,"cix":2,"bm":0,"ix":1,"mn":"ADBE Vector Group","hd":false},{"ty":"gr","it":[{"ty":"gr","it":[{"ty":"gr","it":[{"ind":0,"ty":"sh","ix":1,"ks":{"a":0,"k":{"i":[[0.065,-0.079],[1.091,0.926],[1.227,2.473],[-0.084,3.911],[-2.008,4.444],[-3.796,4.303],[-5.652,3.156],[-0.742,0.35],[-0.761,0.332],[-1.654,0.424],[-3.545,0.197],[-0.898,0.015],[-0.918,-0.164],[-1.725,-0.794],[-2.078,-3.316],[-0.287,-2.888],[0.143,-1.327],[0.087,-1.239],[0,0],[1.685,1.967],[2.728,-0.048],[0.678,-0.09],[0.322,-0.066],[0,0],[1.335,-0.394],[0.664,-0.176],[0.644,-0.212],[1.233,-0.477],[3.601,-2.961],[2.312,-3.213],[1.39,-4.171],[0.173,0.025],[-1.119,4.349],[-4.557,6.819],[-3.653,3.218],[-5.069,2.195],[-1.35,0.425],[-0.678,0.232],[-0.698,0.194],[-1.445,0.322],[0,0],[-0.389,0.059],[-0.796,0.018],[-1.621,-0.513],[-0.75,-0.465],[-0.596,-0.672],[-0.335,-1.688],[0.1,-1.672],[0,0],[0.252,2.354],[1.314,2.099],[3.004,1.384],[1.606,0.267],[0.816,0.041],[0.829,-0.01],[3.064,-0.975],[1.483,-0.525],[0.709,-0.323],[0.662,-0.398],[3.705,-4.068],[1.977,-4.239],[0.217,-3.683],[-1.036,-2.376],[-0.897,-1.054]],"o":[[-0.05,0.064],[-1.047,-0.961],[-1.249,-2.451],[0.081,-3.903],[1.948,-4.468],[3.79,-4.304],[0.691,-0.423],[0.742,-0.348],[1.559,-0.574],[3.239,-1.055],[0.89,-0.015],[0.914,0.04],[1.843,0.298],[3.452,1.581],[1.525,2.458],[0.145,1.441],[-0.149,1.329],[0,0],[0.204,-2.968],[-1.651,-1.99],[-0.687,0.01],[-0.337,0.048],[0,0],[-1.392,0.297],[-0.672,0.178],[-0.652,0.215],[-1.302,0.39],[-4.882,2.032],[-3.565,3.014],[-4.605,6.471],[-1.383,4.198],[-0.158,-0.014],[1.129,-4.321],[2.289,-3.385],[3.688,-3.164],[1.278,-0.517],[0.669,-0.229],[0.689,-0.192],[1.388,-0.425],[0,0],[0.392,-0.085],[0.776,-0.111],[1.588,-0.039],[0.807,0.267],[0.746,0.475],[1.162,1.377],[0.354,1.693],[0,0],[0.166,-2.695],[-0.232,-2.372],[-1.795,-2.862],[-1.5,-0.694],[-0.804,-0.148],[-0.836,0.01],[-3.307,0.17],[-1.562,0.383],[-0.724,0.308],[-0.708,0.325],[-5.413,2.948],[-3.713,4.066],[-2.036,4.218],[-0.215,3.685],[1.015,2.395],[0.938,1.019]],"v":[[-26.294,29.628],[-28.069,28.369],[-31.817,23.351],[-33.817,13.616],[-30.741,0.846],[-22.143,-12.513],[-7.896,-23.921],[-5.726,-25.041],[-3.486,-26.096],[1.259,-27.799],[11.52,-29.591],[14.201,-29.635],[16.971,-29.372],[22.357,-27.733],[30.924,-20.203],[33.751,-12.148],[33.654,-7.952],[33.251,-4.13],[30.617,-4.31],[28.741,-12.26],[21.529,-14.902],[19.476,-14.75],[18.478,-14.582],[17.388,-14.353],[13.268,-13.429],[11.262,-12.897],[9.317,-12.257],[5.557,-10.847],[-7.176,-3.128],[-15.956,6.37],[-24.328,23.052],[-26.294,29.628],[-25.239,22.784],[-17.392,5.371],[-8.522,-4.704],[4.635,-12.992],[8.54,-14.515],[10.561,-15.207],[12.642,-15.787],[16.916,-16.793],[17.961,-17.023],[19.126,-17.232],[21.483,-17.428],[26.336,-16.783],[28.688,-15.691],[30.71,-13.947],[32.953,-9.199],[33.251,-4.13],[30.617,-4.31],[31.101,-11.896],[28.661,-18.787],[21.237,-25.325],[16.547,-26.768],[14.122,-27.008],[11.624,-26.978],[1.991,-25.357],[-2.511,-23.786],[-4.646,-22.804],[-6.721,-21.76],[-20.5,-11.03],[-29.02,1.622],[-32.325,13.675],[-30.872,22.92],[-27.685,27.992]],"c":true},"ix":2},"nm":"Path 1","mn":"ADBE Vector Shape - Group","hd":false},{"ty":"fl","c":{"a":0,"k":[0,0,0,1],"ix":4},"o":{"a":0,"k":100,"ix":5},"r":1,"bm":0,"nm":"Fill 1","mn":"ADBE Vector Graphic - Fill","hd":false},{"ty":"tr","p":{"a":0,"k":[0,0],"ix":2},"a":{"a":0,"k":[0,0],"ix":1},"s":{"a":0,"k":[100,100],"ix":3},"r":{"a":0,"k":0,"ix":6},"o":{"a":0,"k":100,"ix":7},"sk":{"a":0,"k":0,"ix":4},"sa":{"a":0,"k":0,"ix":5},"nm":"Transform"}],"nm":"Group 1","np":2,"cix":2,"bm":0,"ix":1,"mn":"ADBE Vector Group","hd":false},{"ty":"tr","p":{"a":0,"k":[169.01,103.028],"ix":2},"a":{"a":0,"k":[0,0],"ix":1},"s":{"a":0,"k":[100,100],"ix":3},"r":{"a":0,"k":0,"ix":6},"o":{"a":0,"k":100,"ix":7},"sk":{"a":0,"k":0,"ix":4},"sa":{"a":0,"k":0,"ix":5},"nm":"Transform"}],"nm":"Group 1","np":1,"cix":2,"bm":0,"ix":1,"mn":"ADBE Vector Group","hd":false},{"ty":"gr","it":[{"ind":0,"ty":"sh","ix":1,"ks":{"a":0,"k":{"i":[[-8.071,-6.53],[-39.711,7.175],[1.05,-15.393],[1.011,3.867],[8.19,0.281],[7.012,-17.963]],"o":[[0,0],[0,0],[0.263,-3.858],[-2.137,-8.178],[-19.024,-0.653],[-3.583,9.179]],"v":[[-25.991,28.987],[18.22,-16.376],[32.238,-4.862],[32.305,-15.048],[14.622,-28.965],[-30.52,2.748]],"c":true},"ix":2},"nm":"Path 1","mn":"ADBE Vector Shape - Group","hd":false},{"ty":"fl","c":{"a":0,"k":[1,1,1,1],"ix":4},"o":{"a":0,"k":100,"ix":5},"r":1,"bm":0,"nm":"Fill 1","mn":"ADBE Vector Graphic - Fill","hd":false},{"ty":"tr","p":{"a":0,"k":[168.706,103.67],"ix":2},"a":{"a":0,"k":[0,0],"ix":1},"s":{"a":0,"k":[100,100],"ix":3},"r":{"a":0,"k":0,"ix":6},"o":{"a":0,"k":100,"ix":7},"sk":{"a":0,"k":0,"ix":4},"sa":{"a":0,"k":0,"ix":5},"nm":"Transform"}],"nm":"Group 2","np":2,"cix":2,"bm":0,"ix":2,"mn":"ADBE Vector Group","hd":false},{"ty":"tr","p":{"a":0,"k":[168.706,103.67],"ix":2},"a":{"a":0,"k":[168.706,103.67],"ix":1},"s":{"a":0,"k":[100,100],"ix":3},"r":{"a":0,"k":0,"ix":6},"o":{"a":0,"k":100,"ix":7},"sk":{"a":0,"k":0,"ix":4},"sa":{"a":0,"k":0,"ix":5},"nm":"Transform"}],"nm":"Group 2","np":2,"cix":2,"bm":0,"ix":2,"mn":"ADBE Vector Group","hd":false},{"ty":"gr","it":[{"ind":0,"ty":"sh","ix":1,"ks":{"a":0,"k":{"i":[[0,0],[-0.049,-2.048],[0,0],[3.411,1.206]],"o":[[-0.012,2.234],[0,0],[2.243,-3.104],[0,0]],"v":[[-4.991,-3.153],[-4.648,4.103],[3.427,2.566],[2.272,-4.103]],"c":true},"ix":2},"nm":"Path 1","mn":"ADBE Vector Shape - Group","hd":false},{"ty":"fl","c":{"a":0,"k":[0,0,0,1],"ix":4},"o":{"a":0,"k":100,"ix":5},"r":1,"bm":0,"nm":"Fill 1","mn":"ADBE Vector Graphic - Fill","hd":false},{"ty":"tr","p":{"a":0,"k":[173.36,147.094],"ix":2},"a":{"a":0,"k":[0,0],"ix":1},"s":{"a":0,"k":[100,100],"ix":3},"r":{"a":0,"k":0,"ix":6},"o":{"a":0,"k":100,"ix":7},"sk":{"a":0,"k":0,"ix":4},"sa":{"a":0,"k":0,"ix":5},"nm":"Transform"}],"nm":"Group 3","np":2,"cix":2,"bm":0,"ix":3,"mn":"ADBE Vector Group","hd":false},{"ty":"gr","it":[{"ty":"gr","it":[{"ty":"gr","it":[{"ind":0,"ty":"sh","ix":1,"ks":{"a":0,"k":{"i":[[-0.061,0.19],[-2.524,-0.805],[-1.712,-0.841],[-0.912,-0.632],[-0.803,-1.104],[-0.108,-0.838],[0.452,-0.721],[1.347,-0.582],[3.154,-0.269],[7.118,1.345],[3.254,1.111],[2.731,1.819],[0.933,1.553],[-0.148,1.032],[-0.616,0.565],[-1.284,0.416],[-1.191,0.171],[-2.625,-0.236],[0.016,-0.172],[2.604,-0.057],[4.486,-0.85],[1.133,-0.403],[0.76,-0.752],[-0.589,-0.985],[-1.209,-0.779],[-3.121,-1.035],[-3.454,-0.662],[-6.039,0.332],[-2.383,0.89],[-0.48,0.729],[0.526,0.847],[0.782,0.61],[0.775,0.468],[1.177,0.544]],"o":[[0.05,-0.161],[1.261,0.406],[0.852,0.429],[0.909,0.631],[0.37,0.574],[0.134,0.808],[-0.907,1.45],[-2.751,1.13],[-6.317,0.483],[-3.559,-0.682],[-3.249,-1.121],[-1.347,-0.932],[-0.45,-0.772],[0.152,-1.028],[1.266,-1.136],[1.294,-0.398],[4.769,-0.648],[2.627,0.264],[-0.017,0.195],[-2.592,0.081],[-1.115,0.219],[-1.118,0.399],[-0.752,0.779],[0.603,0.964],[2.46,1.567],[3.131,1.032],[6.911,1.308],[3.002,-0.183],[1.177,-0.433],[0.487,-0.694],[-0.53,-0.831],[-0.784,-0.621],[-1.563,-0.922],[-2.359,-1.084]],"v":[[13.711,-5.749],[17.734,-4.882],[22.234,-3.076],[24.905,-1.531],[27.576,0.925],[28.46,2.965],[27.985,5.431],[24.344,8.211],[15.422,10.081],[-4.943,8.713],[-15.196,6.039],[-24.26,1.789],[-27.85,-1.723],[-28.47,-4.537],[-27.118,-6.983],[-23.197,-9.041],[-19.463,-9.854],[-8.232,-10],[-4.196,-9.221],[-8.272,-8.962],[-19.146,-7.993],[-22.547,-7.086],[-25.579,-5.392],[-25.827,-2.914],[-22.902,-0.262],[-14.362,3.56],[-4.442,6.091],[15.251,7.627],[23.514,6.159],[26.225,4.36],[26.019,1.993],[23.904,-0.159],[21.525,-1.762],[17.354,-3.915]],"c":true},"ix":2},"nm":"Path 1","mn":"ADBE Vector Shape - Group","hd":false},{"ty":"fl","c":{"a":0,"k":[0,0,0,1],"ix":4},"o":{"a":0,"k":100,"ix":5},"r":1,"bm":0,"nm":"Fill 1","mn":"ADBE Vector Graphic - Fill","hd":false},{"ty":"tr","p":{"a":0,"k":[0,0],"ix":2},"a":{"a":0,"k":[0,0],"ix":1},"s":{"a":0,"k":[100,100],"ix":3},"r":{"a":0,"k":0,"ix":6},"o":{"a":0,"k":100,"ix":7},"sk":{"a":0,"k":0,"ix":4},"sa":{"a":0,"k":0,"ix":5},"nm":"Transform"}],"nm":"Group 1","np":2,"cix":2,"bm":0,"ix":1,"mn":"ADBE Vector Group","hd":false},{"ty":"tr","p":{"a":0,"k":[164.621,123.215],"ix":2},"a":{"a":0,"k":[0,0],"ix":1},"s":{"a":0,"k":[100,100],"ix":3},"r":{"a":0,"k":0,"ix":6},"o":{"a":0,"k":100,"ix":7},"sk":{"a":0,"k":0,"ix":4},"sa":{"a":0,"k":0,"ix":5},"nm":"Transform"}],"nm":"Group 1","np":1,"cix":2,"bm":0,"ix":1,"mn":"ADBE Vector Group","hd":false},{"ty":"gr","it":[{"ind":0,"ty":"sh","ix":1,"ks":{"a":0,"k":{"i":[[0,0],[0.617,-4],[-15.14,-2.296],[-0.705,4.572],[8.646,2.715]],"o":[[-12.611,-1.122],[-0.705,4.572],[15.14,2.296],[0.495,-3.213],[0,0]],"v":[[-4.275,-8.947],[-27.414,-4.157],[-1.276,8.278],[27.414,4.157],[13.632,-5.475]],"c":false},"ix":2},"nm":"Path 1","mn":"ADBE Vector Shape - Group","hd":false},{"ty":"fl","c":{"a":0,"k":[1,1,1,1],"ix":4},"o":{"a":0,"k":100,"ix":5},"r":1,"bm":0,"nm":"Fill 1","mn":"ADBE Vector Graphic - Fill","hd":false},{"ty":"tr","p":{"a":0,"k":[164.7,122.94],"ix":2},"a":{"a":0,"k":[0,0],"ix":1},"s":{"a":0,"k":[100,100],"ix":3},"r":{"a":0,"k":0,"ix":6},"o":{"a":0,"k":100,"ix":7},"sk":{"a":0,"k":0,"ix":4},"sa":{"a":0,"k":0,"ix":5},"nm":"Transform"}],"nm":"Group 2","np":2,"cix":2,"bm":0,"ix":2,"mn":"ADBE Vector Group","hd":false},{"ty":"tr","p":{"a":0,"k":[164.7,122.94],"ix":2},"a":{"a":0,"k":[164.7,122.94],"ix":1},"s":{"a":0,"k":[100,100],"ix":3},"r":{"a":0,"k":0,"ix":6},"o":{"a":0,"k":100,"ix":7},"sk":{"a":0,"k":0,"ix":4},"sa":{"a":0,"k":0,"ix":5},"nm":"Transform"}],"nm":"Group 4","np":2,"cix":2,"bm":0,"ix":4,"mn":"ADBE Vector Group","hd":false},{"ty":"gr","it":[{"ty":"gr","it":[{"ty":"gr","it":[{"ind":0,"ty":"sh","ix":1,"ks":{"a":0,"k":{"i":[[-0.008,0.092],[-1.638,-0.063],[-3.103,-0.205],[-11.082,-0.898],[-3.024,-0.248],[-1.571,-0.131],[-0.8,-0.067],[-0.592,-0.052],[0,0],[-0.045,-0.069],[0,0],[0,0],[-1.958,-7.115],[-1.291,-7.971],[-0.109,-4.226],[0.322,-2.183],[1.202,-1.952],[1.632,-1.514],[2.307,-0.619],[1.165,0.047],[1.067,0.38],[1.544,1.444],[0.696,0.796],[0.506,0.925],[0.673,1.848],[0.732,3.647],[0.288,6.567],[0.047,1.585],[-0.003,1.524],[0,0],[0.193,-0.022],[0,0],[0.371,0.048],[1.379,0.327],[3.656,2.678],[1.472,2.803],[0.28,1.624],[-0.073,0.009],[-0.446,-1.559],[-1.564,-2.616],[-3.584,-2.407],[-5.328,-1.147],[-1.411,-0.175],[-0.354,-0.039],[-0.596,-0.044],[-0.083,-0.587],[-0.006,-0.501],[-0.024,-1.569],[-0.074,-1.623],[-1.487,-7.11],[-1.291,-3.534],[-0.89,-1.657],[-0.231,-0.406],[-0.208,-0.25],[-0.703,-0.622],[-1.682,-0.67],[-1.706,0.508],[-1.448,1.321],[-1,1.69],[0.017,4.002],[0.603,3.912],[1.858,7.078],[2.018,6.188],[0,0],[0.046,-0.01],[0,0],[0,0],[0.785,0.078],[1.509,0.152],[2.765,0.282],[6.177,0.729],[1.622,0.236]],"o":[[0.008,-0.092],[1.638,0.063],[6.206,0.411],[2.77,0.227],[1.512,0.126],[0.786,0.066],[0.586,0.051],[0,0],[0.095,0.004],[0,0],[0,0],[2.127,6.211],[1.938,7.118],[0.632,3.987],[0.015,2.117],[-0.321,2.148],[-1.162,1.959],[-1.628,1.479],[-1.126,0.355],[-1.174,-0.073],[-2.099,-0.84],[-0.79,-0.709],[-0.762,-0.98],[-0.957,-1.81],[-1.324,-3.703],[-1.456,-7.3],[-0.049,-1.643],[0.003,-1.584],[0,0],[-0.014,-0.077],[0,0],[-0.376,-0.049],[-1.472,-0.212],[-5.511,-1.312],[-3.686,-2.65],[-1.49,-2.814],[-0.284,-1.63],[0.109,-0.017],[0.441,1.555],[1.548,2.608],[3.553,2.432],[1.332,0.286],[0.351,0.039],[0.59,0.043],[0.879,-0.228],[0.006,0.495],[0.023,1.51],[0.071,1.566],[0.379,6.48],[0.746,3.551],[0.654,1.76],[0.214,0.42],[0.235,0.373],[0.613,0.69],[1.377,1.282],[1.692,0.625],[1.712,-0.447],[1.437,-1.333],[1.993,-3.294],[-0.095,-4.036],[-1.232,-7.83],[-1.877,-7.076],[0,0],[-0.015,-0.028],[0,0],[0,0],[-0.799,-0.08],[-1.569,-0.158],[-3.019,-0.308],[-11.059,-1.139],[-3.088,-0.364],[-1.622,-0.236]],"v":[[-33.363,-41.157],[-30.853,-41.196],[-23.701,-40.79],[2.559,-38.8],[11.255,-38.087],[15.881,-37.701],[18.26,-37.501],[20.027,-37.346],[20.303,-37.321],[20.427,-37.101],[20.609,-36.578],[20.927,-35.657],[27.089,-15.644],[32.167,6.982],[33.401,19.292],[33.06,25.737],[30.893,32.169],[26.67,37.36],[20.835,40.851],[17.339,41.223],[13.976,40.473],[8.514,36.932],[6.33,34.652],[4.635,31.911],[2.251,26.405],[-0.772,15.347],[-3.123,-5.553],[-3.267,-10.396],[-3.258,-15.059],[-3.253,-15.829],[-3.377,-16.026],[-3.808,-16.072],[-4.928,-16.217],[-9.205,-17.032],[-23.145,-23.177],[-30.772,-31.798],[-33.152,-38.646],[-33.363,-41.157],[-32.628,-38.769],[-29.867,-32.31],[-22.285,-24.397],[-8.788,-18.873],[-4.668,-18.176],[-3.611,-18.06],[-1.832,-17.929],[-1.218,-16.559],[-1.198,-15.065],[-1.129,-10.445],[-0.912,-5.66],[1.637,14.849],[4.644,25.526],[6.919,30.699],[7.607,31.92],[8.328,32.986],[10.283,35.005],[14.916,38.007],[20.117,38.294],[24.863,35.4],[28.591,30.816],[30.746,19.342],[29.584,7.39],[24.714,-15.004],[18.829,-34.95],[18.754,-35.187],[18.701,-35.265],[18.595,-35.279],[18.06,-35.333],[15.685,-35.57],[11.067,-36.035],[2.386,-36.92],[-23.796,-39.755],[-30.902,-40.661]],"c":true},"ix":2},"nm":"Path 1","mn":"ADBE Vector Shape - Group","hd":false},{"ty":"fl","c":{"a":0,"k":[0,0,0,1],"ix":4},"o":{"a":0,"k":100,"ix":5},"r":1,"bm":0,"nm":"Fill 1","mn":"ADBE Vector Graphic - Fill","hd":false},{"ty":"tr","p":{"a":0,"k":[0,0],"ix":2},"a":{"a":0,"k":[0,0],"ix":1},"s":{"a":0,"k":[100,100],"ix":3},"r":{"a":0,"k":0,"ix":6},"o":{"a":0,"k":100,"ix":7},"sk":{"a":0,"k":0,"ix":4},"sa":{"a":0,"k":0,"ix":5},"nm":"Transform"}],"nm":"Group 1","np":2,"cix":2,"bm":0,"ix":1,"mn":"ADBE Vector Group","hd":false},{"ty":"tr","p":{"a":0,"k":[170.914,161.701],"ix":2},"a":{"a":0,"k":[0,0],"ix":1},"s":{"a":0,"k":[100,100],"ix":3},"r":{"a":0,"k":0,"ix":6},"o":{"a":0,"k":100,"ix":7},"sk":{"a":0,"k":0,"ix":4},"sa":{"a":0,"k":0,"ix":5},"nm":"Transform"}],"nm":"Group 1","np":1,"cix":2,"bm":0,"ix":1,"mn":"ADBE Vector Group","hd":false},{"ty":"gr","it":[{"ind":0,"ty":"sh","ix":1,"ks":{"a":0,"k":{"i":[[0,0],[-5.711,-0.598],[0,0],[-0.049,-2.048],[0,0],[-5.981,3.647],[-1.291,3.543],[0,0]],"o":[[2.864,19.984],[0.903,0.082],[-0.012,2.234],[0.721,33.446],[4.011,4.731],[3.112,-1.886],[5.794,-15.986],[0,0]],"v":[[-32.725,-40.543],[-3.03,-16.447],[-1.601,-16.335],[-1.563,-9.89],[7.924,34.384],[23.732,39.045],[31.529,29.723],[20.181,-35.676]],"c":true},"ix":2},"nm":"Path 1","mn":"ADBE Vector Shape - Group","hd":false},{"ty":"fl","c":{"a":0,"k":[1,1,1,1],"ix":4},"o":{"a":0,"k":100,"ix":5},"r":1,"bm":0,"nm":"Fill 1","mn":"ADBE Vector Graphic - Fill","hd":false},{"ty":"tr","p":{"a":0,"k":[170.275,161.087],"ix":2},"a":{"a":0,"k":[0,0],"ix":1},"s":{"a":0,"k":[100,100],"ix":3},"r":{"a":0,"k":0,"ix":6},"o":{"a":0,"k":100,"ix":7},"sk":{"a":0,"k":0,"ix":4},"sa":{"a":0,"k":0,"ix":5},"nm":"Transform"}],"nm":"Group 2","np":2,"cix":2,"bm":0,"ix":2,"mn":"ADBE Vector Group","hd":false},{"ty":"tr","p":{"a":0,"k":[170.275,161.087],"ix":2},"a":{"a":0,"k":[170.275,161.087],"ix":1},"s":{"a":0,"k":[100,100],"ix":3},"r":{"a":0,"k":0,"ix":6},"o":{"a":0,"k":100,"ix":7},"sk":{"a":0,"k":0,"ix":4},"sa":{"a":0,"k":0,"ix":5},"nm":"Transform"}],"nm":"Group 5","np":2,"cix":2,"bm":0,"ix":5,"mn":"ADBE Vector Group","hd":false},{"ty":"gr","it":[{"ind":0,"ty":"sh","ix":1,"ks":{"a":0,"k":{"i":[[0,0],[24.247,-21.644],[0,0],[14.19,19.317]],"o":[[0,0],[0,0],[0,0],[0,0]],"v":[[-4.288,-20.149],[-12.477,13.773],[0.437,20.149],[7.611,-19.307]],"c":true},"ix":2},"nm":"Path 1","mn":"ADBE Vector Shape - Group","hd":false},{"ty":"fl","c":{"a":0,"k":[0,0,0,1],"ix":4},"o":{"a":0,"k":100,"ix":5},"r":1,"bm":0,"nm":"Fill 1","mn":"ADBE Vector Graphic - Fill","hd":false},{"ty":"tr","p":{"a":0,"k":[189.675,104.288],"ix":2},"a":{"a":0,"k":[0,0],"ix":1},"s":{"a":0,"k":[100,100],"ix":3},"r":{"a":0,"k":0,"ix":6},"o":{"a":0,"k":100,"ix":7},"sk":{"a":0,"k":0,"ix":4},"sa":{"a":0,"k":0,"ix":5},"nm":"Transform"}],"nm":"Group 6","np":2,"cix":2,"bm":0,"ix":6,"mn":"ADBE Vector Group","hd":false},{"ty":"tr","p":{"a":0,"k":[189.675,104.288],"ix":2},"a":{"a":0,"k":[189.675,104.288],"ix":1},"s":{"a":0,"k":[100,100],"ix":3},"r":{"a":0,"k":0,"ix":6},"o":{"a":0,"k":100,"ix":7},"sk":{"a":0,"k":0,"ix":4},"sa":{"a":0,"k":0,"ix":5},"nm":"Transform"}],"nm":"Group 2","np":6,"cix":2,"bm":0,"ix":2,"mn":"ADBE Vector Group","hd":false}],"ip":0,"op":120,"st":0,"ct":1,"bm":0}],"markers":[],"props":{}}